proplot/__init__.py
proplot/colors.py
proplot/config.py
proplot/constructor.py
proplot/crs.py
proplot/demos.py
proplot/figure.py
proplot/gridspec.py
proplot/scale.py
proplot/ticker.py
proplot/ui.py
proplot/utils.py
proplot/axes/__init__.py
proplot/axes/base.py
proplot/axes/cartesian.py
proplot/axes/geo.py
proplot/axes/plot.py
proplot/axes/polar.py
proplot/axes/shared.py
proplot/axes/three.py
proplot/cmaps/Algae.rgb
proplot/cmaps/Amp.rgb
proplot/cmaps/BR.rgb
proplot/cmaps/Balance.rgb
proplot/cmaps/Blues1_r.xml
proplot/cmaps/Blues2.xml
proplot/cmaps/Blues3.xml
proplot/cmaps/Blues4_r.xml
proplot/cmaps/Blues5.xml
proplot/cmaps/Blues6.xml
proplot/cmaps/Blues7.xml
proplot/cmaps/Blues8.xml
proplot/cmaps/Blues9.xml
proplot/cmaps/Boreal.json
proplot/cmaps/Browns1.xml
proplot/cmaps/Browns2.xml
proplot/cmaps/Browns3.xml
proplot/cmaps/Browns4.xml
proplot/cmaps/Browns5.xml
proplot/cmaps/Browns6.xml
proplot/cmaps/Browns7.xml
proplot/cmaps/Browns8.xml
proplot/cmaps/Browns9.xml
proplot/cmaps/ColdHot.rgb
proplot/cmaps/Crest.rgb
proplot/cmaps/Curl.rgb
proplot/cmaps/Deep.rgb
proplot/cmaps/Delta.rgb
proplot/cmaps/Dense.rgb
proplot/cmaps/Div.json
proplot/cmaps/DryWet.json
proplot/cmaps/Dusk.json
proplot/cmaps/Fire.json
proplot/cmaps/Flare.rgb
proplot/cmaps/Glacial.json
proplot/cmaps/Greens1_r.xml
proplot/cmaps/Greens2.xml
proplot/cmaps/Greens3_r.xml
proplot/cmaps/Greens4.xml
proplot/cmaps/Greens5.xml
proplot/cmaps/Greens6_r.xml
proplot/cmaps/Greens7.xml
proplot/cmaps/Greens8.xml
proplot/cmaps/Haline.rgb
proplot/cmaps/Ice.rgb
proplot/cmaps/IceFire.rgb
proplot/cmaps/Mako.rgb
proplot/cmaps/Marine.json
proplot/cmaps/Matter.rgb
proplot/cmaps/Mono.txt
proplot/cmaps/MonoCycle.txt
proplot/cmaps/NegPos.json
proplot/cmaps/Oranges1.xml
proplot/cmaps/Oranges2.xml
proplot/cmaps/Oranges3.xml
proplot/cmaps/Oranges4.xml
proplot/cmaps/Oxy.rgb
proplot/cmaps/Phase.rgb
proplot/cmaps/Purples1_r.xml
proplot/cmaps/Purples2.xml
proplot/cmaps/Purples3.xml
proplot/cmaps/Reds1.xml
proplot/cmaps/Reds2.xml
proplot-0.9.7.dist-info/LICENSE.txt
proplot-0.9.7.dist-info/METADATA
proplot-0.9.7.dist-info/WHEEL
proplot-0.9.7.dist-info/top_level.txt
proplot-0.9.7.dist-info/RECORD
