Metadata-Version: 2.1
Name: proplot
Version: 0.9.7
Summary: A succinct matplotlib wrapper for making beautiful, publication-quality graphics.
Home-page: https://proplot.readthedocs.io
Author: Luke Davis
Author-email: lukelbd@gmail.com
Maintainer: Luke Davis
Maintainer-email: lukelbd@gmail.com
License: MIT
Project-URL: Bug Tracker, https://github.com/lukelbd/proplot/issues
Project-URL: Documentation, https://proplot.readthedocs.io
Project-URL: Source Code, https://github.com/lukelbd/proplot
Classifier: License :: OSI Approved :: MIT License
Classifier: Operating System :: OS Independent
Classifier: Intended Audience :: Science/Research
Classifier: Programming Language :: Python :: 3 :: Only
Classifier: Programming Language :: Python :: 3.6
Classifier: Programming Language :: Python :: 3.7
Classifier: Programming Language :: Python :: 3.8
Requires-Python: >=3.6.0
License-File: LICENSE.txt
